DESCRIPTION.rst
MANIFEST.in
README.rst
git_svn_clone_externals.py
setup.py
git_svn_clone_externals.egg-info/PKG-INFO
git_svn_clone_externals.egg-info/SOURCES.txt
git_svn_clone_externals.egg-info/dependency_links.txt
git_svn_clone_externals.egg-info/entry_points.txt
git_svn_clone_externals.egg-info/pbr.json
git_svn_clone_externals.egg-info/top_level.txt