Metadata-Version: 1.1
Name: git-svn-clone-externals
Version: 1.1.5
Summary: Clone an svn checkout in a tree of nested git-svn repos and helper tools
Home-page: https://github.com/naufraghi/git-svn-clone-externals
Author: Matteo Bertini
Author-email: matteo@naufraghi.net
License: MIT
Keywords: svn git git-svn externals
Platform: UNKNOWN
Classifier: Development Status :: 5 - Production/Stable
Classifier: Intended Audience :: System Administrators
Classifier: Intended Audience :: Developers
Classifier: Environment :: Console
Classifier: License :: OSI Approved :: MIT License
Classifier: Programming Language :: Python :: 2.7
Classifier: Programming Language :: Python :: 3
Classifier: Topic :: Software Development :: Version Control
Classifier: Topic :: Utilities
